netnode/__init__.py
netnode/netnode.py
netnode/test_netnode.py
ida_netnode-3.0.dist-info/LICENSE
ida_netnode-3.0.dist-info/METADATA
ida_netnode-3.0.dist-info/WHEEL
ida_netnode-3.0.dist-info/top_level.txt
ida_netnode-3.0.dist-info/RECORD
