Metadata-Version: 1.1
Name: ida-netnode
Version: 3.0
Summary: Humane API for storing and accessing persistent data in IDA Pro databases
Home-page: https://github.com/williballenthin/ida-netnode
Author: Willi Ballenthin
Author-email: william.ballenthin@fireeye.com
License: Apache License (2.0)
Platform: UNKNOWN
Classifier: Programming Language :: Python
Classifier: Programming Language :: Python :: 2
Classifier: Programming Language :: Python :: 3
Classifier: Operating System :: OS Independent
Classifier: License :: OSI Approved :: Apache Software License
